[
  {
    "match_id": 2757476558,
    "avg": "3875.0000000000000000",
    "count": 1,
    "winrate": 0.5,
    "winrate_wilson": 0.236589593615487,
    "sum": 38750,
    "min": 3875,
    "max": 3875,
    "match_patch": "(2757476558,6.88)",
    "radiant_team_id": 543897,
    "dire_team_id": 3325891,
    "radiant_win": false,
    "radiant_score": 34,
    "dire_score": 62,
    "start_time": 1478335983,
    "League": "SEA Kappa Invitationals"
  },
  {
    "match_id": 2757756308,
    "avg": "3678.0000000000000000",
    "count": 1,
    "winrate": 0.5,
    "winrate_wilson": 0.236589593615487,
    "sum": 36780,
    "min": 3678,
    "max": 3678,
    "match_patch": "(2757756308,6.88)",
    "radiant_team_id": 2208748,
    "dire_team_id": 2854942,
    "radiant_win": false,
    "radiant_score": 31,
    "dire_score": 37,
    "start_time": 1478344107,
    "League": "DOTA2 ACE Provisional"
  },
  {
    "match_id": 2758893203,
    "avg": "3605.0000000000000000",
    "count": 1,
    "winrate": 0.5,
    "winrate_wilson": 0.236589593615487,
    "sum": 36050,
    "min": 3605,
    "max": 3605,
    "match_patch": "(2758893203,6.88)",
    "radiant_team_id": 46,
    "dire_team_id": 2537636,
    "radiant_win": true,
    "radiant_score": 46,
    "dire_score": 42,
    "start_time": 1478372516,
    "League": "ProDotA Cup Series by Azubu.tv"
  },
  {
    "match_id": 2757893940,
    "avg": "3358.0000000000000000",
    "count": 1,
    "winrate": 0.5,
    "winrate_wilson": 0.236589593615487,
    "sum": 33580,
    "min": 3358,
    "max": 3358,
    "match_patch": "(2757893940,6.88)",
    "radiant_team_id": 3327985,
    "dire_team_id": 2659468,
    "radiant_win": false,
    "radiant_score": 38,
    "dire_score": 53,
    "start_time": 1478347583,
    "League": "ProDotA Cup Series by Azubu.tv"
  },
  {
    "match_id": 2758064605,
    "avg": "3302.0000000000000000",
    "count": 1,
    "winrate": 0.5,
    "winrate_wilson": 0.236589593615487,
    "sum": 33020,
    "min": 3302,
    "max": 3302,
    "match_patch": "(2758064605,6.88)",
    "radiant_team_id": 2833547,
    "dire_team_id": 3480835,
    "radiant_win": true,
    "radiant_score": 43,
    "dire_score": 40,
    "start_time": 1478351568,
    "League": "DafaeSports Indonesia Series Presented by Eternal Gaming"
  },
  {
    "match_id": 2758067850,
    "avg": "3095.0000000000000000",
    "count": 1,
    "winrate": 0.5,
    "winrate_wilson": 0.236589593615487,
    "sum": 30950,
    "min": 3095,
    "max": 3095,
    "match_patch": "(2758067850,6.88)",
    "radiant_team_id": 1148284,
    "dire_team_id": 3326875,
    "radiant_win": false,
    "radiant_score": 20,
    "dire_score": 41,
    "start_time": 1478351640,
    "League": "Dota Pit League Season Five"
  },
  {
    "match_id": 2758081275,
    "avg": "2962.0000000000000000",
    "count": 1,
    "winrate": 0.5,
    "winrate_wilson": 0.236589593615487,
    "sum": 29620,
    "min": 2962,
    "max": 2962,
    "match_patch": "(2758081275,6.88)",
    "radiant_team_id": 1520578,
    "dire_team_id": 2626685,
    "radiant_win": true,
    "radiant_score": 37,
    "dire_score": 32,
    "start_time": 1478351942,
    "League": "DOTA2 ACE Provisional"
  },
  {
    "match_id": 2757163100,
    "avg": "2953.0000000000000000",
    "count": 1,
    "winrate": 0.5,
    "winrate_wilson": 0.236589593615487,
    "sum": 29530,
    "min": 2953,
    "max": 2953,
    "match_patch": "(2757163100,6.88)",
    "radiant_team_id": 2634810,
    "dire_team_id": 726228,
    "radiant_win": false,
    "radiant_score": 43,
    "dire_score": 24,
    "start_time": 1478326406,
    "League": "DOTA2 ACE Provisional"
  },
  {
    "match_id": 2757599845,
    "avg": "2951.0000000000000000",
    "count": 1,
    "winrate": 0.5,
    "winrate_wilson": 0.236589593615487,
    "sum": 29510,
    "min": 2951,
    "max": 2951,
    "match_patch": "(2757599845,6.88)",
    "radiant_team_id": 2854942,
    "dire_team_id": 2208748,
    "radiant_win": false,
    "radiant_score": 19,
    "dire_score": 35,
    "start_time": 1478339680,
    "League": "DOTA2 ACE Provisional"
  },
  {
    "match_id": 2757897541,
    "avg": "2841.0000000000000000",
    "count": 1,
    "winrate": 0.5,
    "winrate_wilson": 0.236589593615487,
    "sum": 28410,
    "min": 2841,
    "max": 2841,
    "match_patch": "(2757897541,6.88)",
    "radiant_team_id": 2833547,
    "dire_team_id": 2522510,
    "radiant_win": true,
    "radiant_score": 40,
    "dire_score": 40,
    "start_time": 1478347671,
    "League": "DafaeSports Indonesia Series Presented by Eternal Gaming"
  },
  {
    "match_id": 2757338906,
    "avg": "2840.0000000000000000",
    "count": 1,
    "winrate": 0.5,
    "winrate_wilson": 0.236589593615487,
    "sum": 28400,
    "min": 2840,
    "max": 2840,
    "match_patch": "(2757338906,6.88)",
    "radiant_team_id": 543897,
    "dire_team_id": 3325891,
    "radiant_win": false,
    "radiant_score": 18,
    "dire_score": 46,
    "start_time": 1478331962,
    "League": "SEA Kappa Invitationals"
  },
  {
    "match_id": 2757654862,
    "avg": "2798.0000000000000000",
    "count": 1,
    "winrate": 0.5,
    "winrate_wilson": 0.236589593615487,
    "sum": 27980,
    "min": 2798,
    "max": 2798,
    "match_patch": "(2757654862,6.88)",
    "radiant_team_id": 3410388,
    "dire_team_id": 3212928,
    "radiant_win": true,
    "radiant_score": 50,
    "dire_score": 32,
    "start_time": 1478341279,
    "League": "DafaeSports Indonesia Series Presented by Eternal Gaming"
  },
  {
    "match_id": 2758004354,
    "avg": "2786.0000000000000000",
    "count": 1,
    "winrate": 0.5,
    "winrate_wilson": 0.236589593615487,
    "sum": 27860,
    "min": 2786,
    "max": 2786,
    "match_patch": "(2758004354,6.88)",
    "radiant_team_id": 2634810,
    "dire_team_id": 4,
    "radiant_win": true,
    "radiant_score": 30,
    "dire_score": 36,
    "start_time": 1478350184,
    "League": "DOTA2 ACE Provisional"
  },
  {
    "match_id": 2757489710,
    "avg": "2751.0000000000000000",
    "count": 1,
    "winrate": 0.5,
    "winrate_wilson": 0.236589593615487,
    "sum": 27510,
    "min": 2751,
    "max": 2751,
    "match_patch": "(2757489710,6.88)",
    "radiant_team_id": 5,
    "dire_team_id": 4,
    "radiant_win": true,
    "radiant_score": 30,
    "dire_score": 14,
    "start_time": 1478336371,
    "League": "Dota 2 Professional League 2016"
  },
  {
    "match_id": 2757439302,
    "avg": "2668.0000000000000000",
    "count": 1,
    "winrate": 0.5,
    "winrate_wilson": 0.236589593615487,
    "sum": 26680,
    "min": 2668,
    "max": 2668,
    "match_patch": "(2757439302,6.88)",
    "radiant_team_id": 2414475,
    "dire_team_id": 3258149,
    "radiant_win": true,
    "radiant_score": 29,
    "dire_score": 24,
    "start_time": 1478334903,
    "League": "DOTA2 ACE Provisional"
  },
  {
    "match_id": 2757985506,
    "avg": "2547.0000000000000000",
    "count": 1,
    "winrate": 0.5,
    "winrate_wilson": 0.236589593615487,
    "sum": 25470,
    "min": 2547,
    "max": 2547,
    "match_patch": "(2757985506,6.88)",
    "radiant_team_id": 1218336,
    "dire_team_id": 2486047,
    "radiant_win": true,
    "radiant_score": 32,
    "dire_score": 19,
    "start_time": 1478349748,
    "League": "DafaeSports Indonesia Series Presented by Eternal Gaming"
  },
  {
    "match_id": 2757473622,
    "avg": "2411.0000000000000000",
    "count": 1,
    "winrate": 0.5,
    "winrate_wilson": 0.236589593615487,
    "sum": 24110,
    "min": 2411,
    "max": 2411,
    "match_patch": "(2757473622,6.88)",
    "radiant_team_id": 3327985,
    "dire_team_id": 98301,
    "radiant_win": true,
    "radiant_score": 39,
    "dire_score": 21,
    "start_time": 1478335899,
    "League": "ProDotA Cup Series by Azubu.tv"
  },
  {
    "match_id": 2758104028,
    "avg": "2350.0000000000000000",
    "count": 1,
    "winrate": 0.5,
    "winrate_wilson": 0.236589593615487,
    "sum": 23500,
    "min": 2350,
    "max": 2350,
    "match_patch": "(2758104028,6.88)",
    "radiant_team_id": 2659468,
    "dire_team_id": 3327985,
    "radiant_win": false,
    "radiant_score": 29,
    "dire_score": 40,
    "start_time": 1478352459,
    "League": "ProDotA Cup Series by Azubu.tv"
  },
  {
    "match_id": 2758301876,
    "avg": "2332.0000000000000000",
    "count": 1,
    "winrate": 0.5,
    "winrate_wilson": 0.236589593615487,
    "sum": 23320,
    "min": 2332,
    "max": 2332,
    "match_patch": "(2758301876,6.88)",
    "radiant_team_id": 1218336,
    "dire_team_id": 3482511,
    "radiant_win": false,
    "radiant_score": 22,
    "dire_score": 39,
    "start_time": 1478356892,
    "League": "DafaeSports Indonesia Series Presented by Eternal Gaming"
  },
  {
    "match_id": 2758130654,
    "avg": "2321.0000000000000000",
    "count": 1,
    "winrate": 0.5,
    "winrate_wilson": 0.236589593615487,
    "sum": 23210,
    "min": 2321,
    "max": 2321,
    "match_patch": "(2758130654,6.88)",
    "radiant_team_id": 1836806,
    "dire_team_id": 3331948,
    "radiant_win": false,
    "radiant_score": 17,
    "dire_score": 32,
    "start_time": 1478353060,
    "League": "Dota 2 Professional League 2016"
  },
  {
    "match_id": 2757762156,
    "avg": "2301.0000000000000000",
    "count": 1,
    "winrate": 0.5,
    "winrate_wilson": 0.236589593615487,
    "sum": 23010,
    "min": 2301,
    "max": 2301,
    "match_patch": "(2757762156,6.88)",
    "radiant_team_id": 1375614,
    "dire_team_id": 2640025,
    "radiant_win": false,
    "radiant_score": 27,
    "dire_score": 33,
    "start_time": 1478344261,
    "League": "Dota 2 Professional League 2016"
  },
  {
    "match_id": 2757828149,
    "avg": "2265.0000000000000000",
    "count": 1,
    "winrate": 0.5,
    "winrate_wilson": 0.236589593615487,
    "sum": 22650,
    "min": 2265,
    "max": 2265,
    "match_patch": "(2757828149,6.88)",
    "radiant_team_id": 2581813,
    "dire_team_id": 543897,
    "radiant_win": false,
    "radiant_score": 26,
    "dire_score": 19,
    "start_time": 1478345970,
    "League": "Dota Pit League Season Five"
  },
  {
    "match_id": 2758350891,
    "avg": "2241.0000000000000000",
    "count": 1,
    "winrate": 0.5,
    "winrate_wilson": 0.236589593615487,
    "sum": 22410,
    "min": 2241,
    "max": 2241,
    "match_patch": "(2758350891,6.88)",
    "radiant_team_id": 2662139,
    "dire_team_id": 3444630,
    "radiant_win": false,
    "radiant_score": 22,
    "dire_score": 22,
    "start_time": 1478358083,
    "League": "SEA Kappa Invitationals"
  },
  {
    "match_id": 2757679066,
    "avg": "2221.0000000000000000",
    "count": 1,
    "winrate": 0.5,
    "winrate_wilson": 0.236589593615487,
    "sum": 22210,
    "min": 2221,
    "max": 2221,
    "match_patch": "(2757679066,6.88)",
    "radiant_team_id": 2581813,
    "dire_team_id": 543897,
    "radiant_win": false,
    "radiant_score": 15,
    "dire_score": 33,
    "start_time": 1478341985,
    "League": "Dota Pit League Season Five"
  },
  {
    "match_id": 2757940240,
    "avg": "2178.0000000000000000",
    "count": 1,
    "winrate": 0.5,
    "winrate_wilson": 0.236589593615487,
    "sum": 21780,
    "min": 2178,
    "max": 2178,
    "match_patch": "(2757940240,6.88)",
    "radiant_team_id": 1520578,
    "dire_team_id": 2626685,
    "radiant_win": true,
    "radiant_score": 47,
    "dire_score": 29,
    "start_time": 1478348679,
    "League": "DOTA2 ACE Provisional"
  },
  {
    "match_id": 2757243157,
    "avg": "2152.0000000000000000",
    "count": 1,
    "winrate": 0.5,
    "winrate_wilson": 0.236589593615487,
    "sum": 21520,
    "min": 2152,
    "max": 2152,
    "match_patch": "(2757243157,6.88)",
    "radiant_team_id": 3325891,
    "dire_team_id": 543897,
    "radiant_win": false,
    "radiant_score": 19,
    "dire_score": 28,
    "start_time": 1478329015,
    "League": "SEA Kappa Invitationals"
  },
  {
    "match_id": 2759026966,
    "avg": "2017.0000000000000000",
    "count": 1,
    "winrate": 0.5,
    "winrate_wilson": 0.236589593615487,
    "sum": 20170,
    "min": 2017,
    "max": 2017,
    "match_patch": "(2759026966,6.88)",
    "radiant_team_id": 2537636,
    "dire_team_id": 46,
    "radiant_win": false,
    "radiant_score": 28,
    "dire_score": 26,
    "start_time": 1478377218,
    "League": "ProDotA Cup Series by Azubu.tv"
  },
  {
    "match_id": 2757597788,
    "avg": "1922.0000000000000000",
    "count": 1,
    "winrate": 0.5,
    "winrate_wilson": 0.236589593615487,
    "sum": 19220,
    "min": 1922,
    "max": 1922,
    "match_patch": "(2757597788,6.88)",
    "radiant_team_id": 98301,
    "dire_team_id": 3327985,
    "radiant_win": false,
    "radiant_score": 24,
    "dire_score": 26,
    "start_time": 1478339619,
    "League": "ProDotA Cup Series by Azubu.tv"
  },
  {
    "match_id": 2757356922,
    "avg": "1908.0000000000000000",
    "count": 1,
    "winrate": 0.5,
    "winrate_wilson": 0.236589593615487,
    "sum": 19080,
    "min": 1908,
    "max": 1908,
    "match_patch": "(2757356922,6.88)",
    "radiant_team_id": 2414095,
    "dire_team_id": 1375614,
    "radiant_win": false,
    "radiant_score": 22,
    "dire_score": 25,
    "start_time": 1478332501,
    "League": "DOTA2 ACE Provisional"
  },
  {
    "match_id": 2758260813,
    "avg": "1813.0000000000000000",
    "count": 1,
    "winrate": 0.5,
    "winrate_wilson": 0.236589593615487,
    "sum": 18130,
    "min": 1813,
    "max": 1813,
    "match_patch": "(2758260813,6.88)",
    "radiant_team_id": 2833547,
    "dire_team_id": 3471400,
    "radiant_win": false,
    "radiant_score": 15,
    "dire_score": 39,
    "start_time": 1478355988,
    "League": "DafaeSports Indonesia Series Presented by Eternal Gaming"
  },
  {
    "match_id": 2758457009,
    "avg": "1762.0000000000000000",
    "count": 1,
    "winrate": 0.5,
    "winrate_wilson": 0.236589593615487,
    "sum": 17620,
    "min": 1762,
    "max": 1762,
    "match_patch": "(2758457009,6.88)",
    "radiant_team_id": 3471400,
    "dire_team_id": 3482511,
    "radiant_win": true,
    "radiant_score": 36,
    "dire_score": 14,
    "start_time": 1478360662,
    "League": "DafaeSports Indonesia Series Presented by Eternal Gaming"
  },
  {
    "match_id": 2757656889,
    "avg": "1751.0000000000000000",
    "count": 1,
    "winrate": 0.5,
    "winrate_wilson": 0.236589593615487,
    "sum": 17510,
    "min": 1751,
    "max": 1751,
    "match_patch": "(2757656889,6.88)",
    "radiant_team_id": 2640025,
    "dire_team_id": 1375614,
    "radiant_win": false,
    "radiant_score": 11,
    "dire_score": 26,
    "start_time": 1478341338,
    "League": "Dota 2 Professional League 2016"
  },
  {
    "match_id": 2758278693,
    "avg": "1749.0000000000000000",
    "count": 1,
    "winrate": 0.5,
    "winrate_wilson": 0.236589593615487,
    "sum": 17490,
    "min": 1749,
    "max": 1749,
    "match_patch": "(2758278693,6.88)",
    "radiant_team_id": 1148284,
    "dire_team_id": 3326875,
    "radiant_win": false,
    "radiant_score": 15,
    "dire_score": 34,
    "start_time": 1478356378,
    "League": "Dota Pit League Season Five"
  },
  {
    "match_id": 2757239088,
    "avg": "1690.0000000000000000",
    "count": 1,
    "winrate": 0.5,
    "winrate_wilson": 0.236589593615487,
    "sum": 16900,
    "min": 1690,
    "max": 1690,
    "match_patch": "(2757239088,6.88)",
    "radiant_team_id": 15,
    "dire_team_id": 2833354,
    "radiant_win": true,
    "radiant_score": 15,
    "dire_score": 8,
    "start_time": 1478328886,
    "League": "DOTA2 ACE Provisional"
  },
  {
    "match_id": 2757790759,
    "avg": "1468.0000000000000000",
    "count": 1,
    "winrate": 0.5,
    "winrate_wilson": 0.236589593615487,
    "sum": 14680,
    "min": 1468,
    "max": 1468,
    "match_patch": "(2757790759,6.88)",
    "radiant_team_id": 2659468,
    "dire_team_id": 3327985,
    "radiant_win": false,
    "radiant_score": 10,
    "dire_score": 38,
    "start_time": 1478345012,
    "League": "ProDotA Cup Series by Azubu.tv"
  },
  {
    "match_id": 2757397620,
    "avg": "1458.0000000000000000",
    "count": 1,
    "winrate": 0.5,
    "winrate_wilson": 0.236589593615487,
    "sum": 14580,
    "min": 1458,
    "max": 1458,
    "match_patch": "(2757397620,6.88)",
    "radiant_team_id": 4,
    "dire_team_id": 5,
    "radiant_win": false,
    "radiant_score": 1,
    "dire_score": 22,
    "start_time": 1478333698,
    "League": "Dota 2 Professional League 2016"
  },
  {
    "match_id": 2757628868,
    "avg": "1446.0000000000000000",
    "count": 1,
    "winrate": 0.5,
    "winrate_wilson": 0.236589593615487,
    "sum": 14460,
    "min": 1446,
    "max": 1446,
    "match_patch": "(2757628868,6.88)",
    "radiant_team_id": 2860081,
    "dire_team_id": 1520578,
    "radiant_win": false,
    "radiant_score": 11,
    "dire_score": 22,
    "start_time": 1478340521,
    "League": "DOTA2 ACE Provisional"
  },
  {
    "match_id": 2757371712,
    "avg": "1421.0000000000000000",
    "count": 1,
    "winrate": 0.5,
    "winrate_wilson": 0.236589593615487,
    "sum": 14210,
    "min": 1421,
    "max": 1421,
    "match_patch": "(2757371712,6.88)",
    "radiant_team_id": 98301,
    "dire_team_id": 3327985,
    "radiant_win": true,
    "radiant_score": 23,
    "dire_score": 7,
    "start_time": 1478332942,
    "League": "ProDotA Cup Series by Azubu.tv"
  },
  {
    "match_id": 2758014435,
    "avg": "1354.0000000000000000",
    "count": 1,
    "winrate": 0.5,
    "winrate_wilson": 0.236589593615487,
    "sum": 13540,
    "min": 1354,
    "max": 1354,
    "match_patch": "(2758014435,6.88)",
    "radiant_team_id": 1836806,
    "dire_team_id": 3331948,
    "radiant_win": false,
    "radiant_score": 9,
    "dire_score": 34,
    "start_time": 1478350416,
    "League": "Dota 2 Professional League 2016"
  },
  {
    "match_id": 2758230626,
    "avg": "1312.0000000000000000",
    "count": 1,
    "winrate": 0.5,
    "winrate_wilson": 0.236589593615487,
    "sum": 13120,
    "min": 1312,
    "max": 1312,
    "match_patch": "(2758230626,6.88)",
    "radiant_team_id": 3444630,
    "dire_team_id": 2662139,
    "radiant_win": true,
    "radiant_score": 25,
    "dire_score": 9,
    "start_time": 1478355292,
    "League": "SEA Kappa Invitationals"
  },
  {
    "match_id": 2757150100,
    "avg": "1304.0000000000000000",
    "count": 1,
    "winrate": 0.5,
    "winrate_wilson": 0.236589593615487,
    "sum": 13040,
    "min": 1304,
    "max": 1304,
    "match_patch": "(2757150100,6.88)",
    "radiant_team_id": 15,
    "dire_team_id": 2833354,
    "radiant_win": true,
    "radiant_score": 7,
    "dire_score": 4,
    "start_time": 1478325970,
    "League": "DOTA2 ACE Provisional"
  },
  {
    "match_id": 2757358711,
    "avg": "1283.0000000000000000",
    "count": 1,
    "winrate": 0.5,
    "winrate_wilson": 0.236589593615487,
    "sum": 12830,
    "min": 1283,
    "max": 1283,
    "match_patch": "(2757358711,6.88)",
    "radiant_team_id": 3258149,
    "dire_team_id": 2414475,
    "radiant_win": false,
    "radiant_score": 4,
    "dire_score": 18,
    "start_time": 1478332552,
    "League": "DOTA2 ACE Provisional"
  },
  {
    "match_id": 2757141172,
    "avg": "1217.0000000000000000",
    "count": 1,
    "winrate": 0.5,
    "winrate_wilson": 0.236589593615487,
    "sum": 12170,
    "min": 1217,
    "max": 1217,
    "match_patch": "(2757141172,6.88)",
    "radiant_team_id": 4,
    "dire_team_id": 1520578,
    "radiant_win": false,
    "radiant_score": 10,
    "dire_score": 25,
    "start_time": 1478325656,
    "League": "Dota 2 Professional League 2016"
  },
  {
    "match_id": 2757203104,
    "avg": "1177.0000000000000000",
    "count": 1,
    "winrate": 0.5,
    "winrate_wilson": 0.236589593615487,
    "sum": 11770,
    "min": 1177,
    "max": 1177,
    "match_patch": "(2757203104,6.88)",
    "radiant_team_id": 4,
    "dire_team_id": 1520578,
    "radiant_win": true,
    "radiant_score": 19,
    "dire_score": 5,
    "start_time": 1478327728,
    "League": "Dota 2 Professional League 2016"
  },
  {
    "match_id": 2757464552,
    "avg": "1090.0000000000000000",
    "count": 1,
    "winrate": 0.5,
    "winrate_wilson": 0.236589593615487,
    "sum": 10900,
    "min": 1090,
    "max": 1090,
    "match_patch": "(2757464552,6.88)",
    "radiant_team_id": 2414095,
    "dire_team_id": 1375614,
    "radiant_win": false,
    "radiant_score": 6,
    "dire_score": 30,
    "start_time": 1478335636,
    "League": "DOTA2 ACE Provisional"
  },
  {
    "match_id": 2757907171,
    "avg": "1002.0000000000000000",
    "count": 1,
    "winrate": 0.5,
    "winrate_wilson": 0.236589593615487,
    "sum": 10020,
    "min": 1002,
    "max": 1002,
    "match_patch": "(2757907171,6.88)",
    "radiant_team_id": 2634810,
    "dire_team_id": 4,
    "radiant_win": false,
    "radiant_score": 6,
    "dire_score": 18,
    "start_time": 1478347901,
    "League": "DOTA2 ACE Provisional"
  },
  {
    "match_id": 2757288592,
    "avg": "780.0000000000000000",
    "count": 1,
    "winrate": 0.5,
    "winrate_wilson": 0.236589593615487,
    "sum": 7800,
    "min": 780,
    "max": 780,
    "match_patch": "(2757288592,6.88)",
    "radiant_team_id": 2634810,
    "dire_team_id": 726228,
    "radiant_win": false,
    "radiant_score": 5,
    "dire_score": 18,
    "start_time": 1478330436,
    "League": "DOTA2 ACE Provisional"
  },
  {
    "match_id": 2757724097,
    "avg": "773.0000000000000000",
    "count": 1,
    "winrate": 0.5,
    "winrate_wilson": 0.236589593615487,
    "sum": 7730,
    "min": 773,
    "max": 773,
    "match_patch": "(2757724097,6.88)",
    "radiant_team_id": 2860081,
    "dire_team_id": 1520578,
    "radiant_win": false,
    "radiant_score": 4,
    "dire_score": 13,
    "start_time": 1478343256,
    "League": "DOTA2 ACE Provisional"
  }
]
