[
  {
    "match_id": 2364826014,
    "avg": "4496.0000000000000000",
    "count": 1,
    "winrate": 0.5,
    "winrate_wilson": 0.236589593615487,
    "sum": 44960,
    "min": 4496,
    "max": 4496,
    "match_patch": "(2364826014,6.87)",
    "radiant_team_id": 2839755,
    "dire_team_id": 2799715,
    "radiant_win": true,
    "radiant_score": 55,
    "dire_score": 37,
    "start_time": 1463308099,
    "League": "CyberGamer Pro Leagues Season 3"
  },
  {
    "match_id": 2366053329,
    "avg": "3180.0000000000000000",
    "count": 1,
    "winrate": 0.5,
    "winrate_wilson": 0.236589593615487,
    "sum": 31800,
    "min": 3180,
    "max": 3180,
    "match_patch": "(2366053329,6.87)",
    "radiant_team_id": null,
    "dire_team_id": 1633432,
    "radiant_win": false,
    "radiant_score": 34,
    "dire_score": 34,
    "start_time": 1463344361,
    "League": "Sudamerican Master 4"
  },
  {
    "match_id": 2366216139,
    "avg": "2956.0000000000000000",
    "count": 1,
    "winrate": 0.5,
    "winrate_wilson": 0.236589593615487,
    "sum": 29560,
    "min": 2956,
    "max": 2956,
    "match_patch": "(2366216139,6.87)",
    "radiant_team_id": null,
    "dire_team_id": 1633432,
    "radiant_win": true,
    "radiant_score": 42,
    "dire_score": 40,
    "start_time": 1463354120,
    "League": "Sudamerican Master 4"
  },
  {
    "match_id": 2365504209,
    "avg": "2925.0000000000000000",
    "count": 1,
    "winrate": 0.5,
    "winrate_wilson": 0.236589593615487,
    "sum": 29250,
    "min": 2925,
    "max": 2925,
    "match_patch": "(2365504209,6.87)",
    "radiant_team_id": null,
    "dire_team_id": 2835573,
    "radiant_win": true,
    "radiant_score": 45,
    "dire_score": 33,
    "start_time": 1463325283,
    "League": "The Battle Fury 2015"
  },
  {
    "match_id": 2366154317,
    "avg": "2855.0000000000000000",
    "count": 1,
    "winrate": 0.5,
    "winrate_wilson": 0.236589593615487,
    "sum": 28550,
    "min": 2855,
    "max": 2855,
    "match_patch": "(2366154317,6.87)",
    "radiant_team_id": null,
    "dire_team_id": 1633432,
    "radiant_win": true,
    "radiant_score": 40,
    "dire_score": 50,
    "start_time": 1463349884,
    "League": "Sudamerican Master 4"
  },
  {
    "match_id": 2365660179,
    "avg": "2789.0000000000000000",
    "count": 1,
    "winrate": 0.5,
    "winrate_wilson": 0.236589593615487,
    "sum": 27890,
    "min": 2789,
    "max": 2789,
    "match_patch": "(2365660179,6.87)",
    "radiant_team_id": 2835573,
    "dire_team_id": null,
    "radiant_win": false,
    "radiant_score": 42,
    "dire_score": 47,
    "start_time": 1463329726,
    "League": "The Battle Fury 2015"
  },
  {
    "match_id": 2366096754,
    "avg": "2741.0000000000000000",
    "count": 1,
    "winrate": 0.5,
    "winrate_wilson": 0.236589593615487,
    "sum": 27410,
    "min": 2741,
    "max": 2741,
    "match_patch": "(2366096754,6.87)",
    "radiant_team_id": null,
    "dire_team_id": null,
    "radiant_win": false,
    "radiant_score": 21,
    "dire_score": 35,
    "start_time": 1463346554,
    "League": "The Battle Fury 2015"
  },
  {
    "match_id": 2366143808,
    "avg": "2435.0000000000000000",
    "count": 1,
    "winrate": 0.5,
    "winrate_wilson": 0.236589593615487,
    "sum": 24350,
    "min": 2435,
    "max": 2435,
    "match_patch": "(2366143808,6.87)",
    "radiant_team_id": null,
    "dire_team_id": 2217730,
    "radiant_win": false,
    "radiant_score": 20,
    "dire_score": 26,
    "start_time": 1463349232,
    "League": "ProDotA Cup by Azubu.tv"
  },
  {
    "match_id": 2366012518,
    "avg": "2339.0000000000000000",
    "count": 1,
    "winrate": 0.5,
    "winrate_wilson": 0.236589593615487,
    "sum": 23390,
    "min": 2339,
    "max": 2339,
    "match_patch": "(2366012518,6.87)",
    "radiant_team_id": null,
    "dire_team_id": null,
    "radiant_win": false,
    "radiant_score": 6,
    "dire_score": 21,
    "start_time": 1463342523,
    "League": "The Battle Fury 2015"
  },
  {
    "match_id": 2365016474,
    "avg": "2314.0000000000000000",
    "count": 1,
    "winrate": 0.5,
    "winrate_wilson": 0.236589593615487,
    "sum": 23140,
    "min": 2314,
    "max": 2314,
    "match_patch": "(2365016474,6.87)",
    "radiant_team_id": null,
    "dire_team_id": 1226701,
    "radiant_win": true,
    "radiant_score": 48,
    "dire_score": 19,
    "start_time": 1463313346,
    "League": "SL i-League StarSeries S2"
  },
  {
    "match_id": 2366249931,
    "avg": "2181.0000000000000000",
    "count": 1,
    "winrate": 0.5,
    "winrate_wilson": 0.236589593615487,
    "sum": 21810,
    "min": 2181,
    "max": 2181,
    "match_patch": "(2366249931,6.87)",
    "radiant_team_id": 67,
    "dire_team_id": 2837183,
    "radiant_win": false,
    "radiant_score": 11,
    "dire_score": 29,
    "start_time": 1463356715,
    "League": "ProDotA Cup by Azubu.tv"
  },
  {
    "match_id": 2365475653,
    "avg": "2137.0000000000000000",
    "count": 1,
    "winrate": 0.5,
    "winrate_wilson": 0.236589593615487,
    "sum": 21370,
    "min": 2137,
    "max": 2137,
    "match_patch": "(2365475653,6.87)",
    "radiant_team_id": 2762745,
    "dire_team_id": null,
    "radiant_win": false,
    "radiant_score": 17,
    "dire_score": 28,
    "start_time": 1463324513,
    "League": "SL i-League StarSeries S2"
  },
  {
    "match_id": 2364775806,
    "avg": "2045.0000000000000000",
    "count": 1,
    "winrate": 0.5,
    "winrate_wilson": 0.236589593615487,
    "sum": 20450,
    "min": 2045,
    "max": 2045,
    "match_patch": "(2364775806,6.87)",
    "radiant_team_id": 2098902,
    "dire_team_id": 2741983,
    "radiant_win": false,
    "radiant_score": 6,
    "dire_score": 34,
    "start_time": 1463306684,
    "League": "CyberGamer Pro Leagues Season 3"
  },
  {
    "match_id": 2365614598,
    "avg": "2041.0000000000000000",
    "count": 1,
    "winrate": 0.5,
    "winrate_wilson": 0.236589593615487,
    "sum": 20410,
    "min": 2041,
    "max": 2041,
    "match_patch": "(2365614598,6.87)",
    "radiant_team_id": null,
    "dire_team_id": 2762745,
    "radiant_win": true,
    "radiant_score": 47,
    "dire_score": 13,
    "start_time": 1463328349,
    "League": "SL i-League StarSeries S2"
  },
  {
    "match_id": 2364629627,
    "avg": "2010.0000000000000000",
    "count": 1,
    "winrate": 0.5,
    "winrate_wilson": 0.236589593615487,
    "sum": 20100,
    "min": 2010,
    "max": 2010,
    "match_patch": "(2364629627,6.87)",
    "radiant_team_id": 2581813,
    "dire_team_id": null,
    "radiant_win": false,
    "radiant_score": 10,
    "dire_score": 22,
    "start_time": 1463302886,
    "League": "The Summit 5"
  },
  {
    "match_id": 2364890202,
    "avg": "1895.0000000000000000",
    "count": 1,
    "winrate": 0.5,
    "winrate_wilson": 0.236589593615487,
    "sum": 18950,
    "min": 1895,
    "max": 1895,
    "match_patch": "(2364890202,6.87)",
    "radiant_team_id": 1226701,
    "dire_team_id": null,
    "radiant_win": false,
    "radiant_score": 10,
    "dire_score": 28,
    "start_time": 1463309963,
    "League": "SL i-League StarSeries S2"
  },
  {
    "match_id": 2364754785,
    "avg": "1889.0000000000000000",
    "count": 1,
    "winrate": 0.5,
    "winrate_wilson": 0.236589593615487,
    "sum": 18890,
    "min": 1889,
    "max": 1889,
    "match_patch": "(2364754785,6.87)",
    "radiant_team_id": 2581813,
    "dire_team_id": null,
    "radiant_win": true,
    "radiant_score": 20,
    "dire_score": 11,
    "start_time": 1463306113,
    "League": "The Summit 5"
  },
  {
    "match_id": 2365061892,
    "avg": "1704.0000000000000000",
    "count": 1,
    "winrate": 0.5,
    "winrate_wilson": 0.236589593615487,
    "sum": 17040,
    "min": 1704,
    "max": 1704,
    "match_patch": "(2365061892,6.87)",
    "radiant_team_id": 1421914,
    "dire_team_id": 2755844,
    "radiant_win": false,
    "radiant_score": 19,
    "dire_score": 37,
    "start_time": 1463314534,
    "League": "SGC 2016"
  },
  {
    "match_id": 2363757344,
    "avg": "1650.0000000000000000",
    "count": 1,
    "winrate": 0.5,
    "winrate_wilson": 0.236589593615487,
    "sum": 16500,
    "min": 1650,
    "max": 1650,
    "match_patch": "(2363757344,6.87)",
    "radiant_team_id": 2791586,
    "dire_team_id": null,
    "radiant_win": false,
    "radiant_score": 15,
    "dire_score": 30,
    "start_time": 1463273167,
    "League": "ProDotA Cup by Azubu.tv"
  },
  {
    "match_id": 2366092567,
    "avg": "1629.0000000000000000",
    "count": 1,
    "winrate": 0.5,
    "winrate_wilson": 0.236589593615487,
    "sum": 16290,
    "min": 1629,
    "max": 1629,
    "match_patch": "(2366092567,6.87)",
    "radiant_team_id": null,
    "dire_team_id": 2217730,
    "radiant_win": false,
    "radiant_score": 11,
    "dire_score": 25,
    "start_time": 1463346333,
    "League": "ProDotA Cup by Azubu.tv"
  },
  {
    "match_id": 2364921432,
    "avg": "1444.0000000000000000",
    "count": 1,
    "winrate": 0.5,
    "winrate_wilson": 0.236589593615487,
    "sum": 14440,
    "min": 1444,
    "max": 1444,
    "match_patch": "(2364921432,6.87)",
    "radiant_team_id": 2755844,
    "dire_team_id": 1421914,
    "radiant_win": true,
    "radiant_score": 33,
    "dire_score": 13,
    "start_time": 1463310810,
    "League": "SGC 2016"
  },
  {
    "match_id": 2366128921,
    "avg": "1360.0000000000000000",
    "count": 1,
    "winrate": 0.5,
    "winrate_wilson": 0.236589593615487,
    "sum": 13600,
    "min": 1360,
    "max": 1360,
    "match_patch": "(2366128921,6.87)",
    "radiant_team_id": 2701329,
    "dire_team_id": 2837183,
    "radiant_win": true,
    "radiant_score": 26,
    "dire_score": 18,
    "start_time": 1463348343,
    "League": "ProDotA Cup by Azubu.tv"
  },
  {
    "match_id": 2366079064,
    "avg": "1342.0000000000000000",
    "count": 1,
    "winrate": 0.5,
    "winrate_wilson": 0.236589593615487,
    "sum": 13420,
    "min": 1342,
    "max": 1342,
    "match_patch": "(2366079064,6.87)",
    "radiant_team_id": 2837183,
    "dire_team_id": 2701329,
    "radiant_win": false,
    "radiant_score": 10,
    "dire_score": 24,
    "start_time": 1463345646,
    "League": "ProDotA Cup by Azubu.tv"
  },
  {
    "match_id": 2365205808,
    "avg": "1230.0000000000000000",
    "count": 1,
    "winrate": 0.5,
    "winrate_wilson": 0.236589593615487,
    "sum": 12300,
    "min": 1230,
    "max": 1230,
    "match_patch": "(2365205808,6.87)",
    "radiant_team_id": 2780729,
    "dire_team_id": 2789230,
    "radiant_win": true,
    "radiant_score": 22,
    "dire_score": 5,
    "start_time": 1463318101,
    "League": "SGC 2016"
  },
  {
    "match_id": 2365323344,
    "avg": "1207.0000000000000000",
    "count": 1,
    "winrate": 0.5,
    "winrate_wilson": 0.236589593615487,
    "sum": 12070,
    "min": 1207,
    "max": 1207,
    "match_patch": "(2365323344,6.87)",
    "radiant_team_id": 2789230,
    "dire_team_id": 2780729,
    "radiant_win": false,
    "radiant_score": 3,
    "dire_score": 18,
    "start_time": 1463320835,
    "League": "SGC 2016"
  }
]
