[
  {
    "date": "2016-07-21T00:00:00.000Z",
    "match_id": 2517642379,
    "duration (seconds)": 1246,
    "match_patch": "(2517642379,6.88)",
    "Radiant Team": "Infamous、",
    "radiant_score": 24,
    "Dire Team": "Luccini Gaming",
    "dire_score": 18,
    "Winner": "Radiant"
  },
  {
    "date": "2016-07-21T00:00:00.000Z",
    "match_id": 2517688499,
    "duration (seconds)": 2413,
    "match_patch": "(2517688499,6.88)",
    "Radiant Team": "Luccini Gaming",
    "radiant_score": 31,
    "Dire Team": "Infamous、",
    "dire_score": 37,
    "Winner": "Dire"
  },
  {
    "date": "2016-07-21T00:00:00.000Z",
    "match_id": 2518063442,
    "duration (seconds)": 3564,
    "match_patch": "(2518063442,6.88)",
    "Radiant Team": "To.be.or.not.to.be",
    "radiant_score": 31,
    "Dire Team": "KEEN GAMING",
    "dire_score": 47,
    "Winner": "Dire"
  },
  {
    "date": "2016-07-21T00:00:00.000Z",
    "match_id": 2518077827,
    "duration (seconds)": 1935,
    "match_patch": "(2518077827,6.88)",
    "Radiant Team": null,
    "radiant_score": 12,
    "Dire Team": "iG.Vitality",
    "dire_score": 25,
    "Winner": "Dire"
  },
  {
    "date": "2016-07-21T00:00:00.000Z",
    "match_id": 2518182762,
    "duration (seconds)": 1706,
    "match_patch": "(2518182762,6.88)",
    "Radiant Team": "team_ftd_a",
    "radiant_score": 10,
    "Dire Team": "iG.Vitality",
    "dire_score": 31,
    "Winner": "Dire"
  },
  {
    "date": "2016-07-21T00:00:00.000Z",
    "match_id": 2518204894,
    "duration (seconds)": 1940,
    "match_patch": "(2518204894,6.88)",
    "Radiant Team": "",
    "radiant_score": 40,
    "Dire Team": "Team VDuoBao",
    "dire_score": 20,
    "Winner": "Radiant"
  },
  {
    "date": "2016-07-21T00:00:00.000Z",
    "match_id": 2518310741,
    "duration (seconds)": 2251,
    "match_patch": "(2518310741,6.88)",
    "Radiant Team": "",
    "radiant_score": 21,
    "Dire Team": "iG.Vitality",
    "dire_score": 19,
    "Winner": "Dire"
  },
  {
    "date": "2016-07-21T00:00:00.000Z",
    "match_id": 2518311144,
    "duration (seconds)": 1810,
    "match_patch": "(2518311144,6.88)",
    "Radiant Team": "CDEC.Avenger",
    "radiant_score": 17,
    "Dire Team": "KEEN GAMING",
    "dire_score": 14,
    "Winner": "Radiant"
  },
  {
    "date": "2016-07-21T00:00:00.000Z",
    "match_id": 2518418001,
    "duration (seconds)": 1783,
    "match_patch": "(2518418001,6.88)",
    "Radiant Team": "FTD club a",
    "radiant_score": 32,
    "Dire Team": "We.are.young",
    "dire_score": 7,
    "Winner": "Radiant"
  },
  {
    "date": "2016-07-21T00:00:00.000Z",
    "match_id": 2518455526,
    "duration (seconds)": 1475,
    "match_patch": "(2518455526,6.88)",
    "Radiant Team": "Beyond_Infinity",
    "radiant_score": 8,
    "Dire Team": "",
    "dire_score": 21,
    "Winner": "Dire"
  },
  {
    "date": "2016-07-21T00:00:00.000Z",
    "match_id": 2518471287,
    "duration (seconds)": 1559,
    "match_patch": "(2518471287,6.88)",
    "Radiant Team": "CDEC Gaming",
    "radiant_score": 13,
    "Dire Team": "Team Braveheart",
    "dire_score": 29,
    "Winner": "Dire"
  },
  {
    "date": "2016-07-21T00:00:00.000Z",
    "match_id": 2518557831,
    "duration (seconds)": 1793,
    "match_patch": "(2518557831,6.88)",
    "Radiant Team": "CDEC Gaming",
    "radiant_score": 12,
    "Dire Team": "FTD club a",
    "dire_score": 31,
    "Winner": "Dire"
  },
  {
    "date": "2016-07-21T00:00:00.000Z",
    "match_id": 2518557862,
    "duration (seconds)": 3467,
    "match_patch": "(2518557862,6.88)",
    "Radiant Team": "Beyond_Infinity",
    "radiant_score": 36,
    "Dire Team": "",
    "dire_score": 30,
    "Winner": "Radiant"
  },
  {
    "date": "2016-07-21T00:00:00.000Z",
    "match_id": 2518561906,
    "duration (seconds)": 2163,
    "match_patch": "(2518561906,6.88)",
    "Radiant Team": "We.are.young",
    "radiant_score": 24,
    "Dire Team": "Team Braveheart",
    "dire_score": 42,
    "Winner": "Dire"
  },
  {
    "date": "2016-07-21T00:00:00.000Z",
    "match_id": 2518745501,
    "duration (seconds)": 2375,
    "match_patch": "(2518745501,6.88)",
    "Radiant Team": "stealth._.gaming",
    "radiant_score": 17,
    "Dire Team": "Aggressive 5",
    "dire_score": 34,
    "Winner": "Dire"
  },
  {
    "date": "2016-07-21T00:00:00.000Z",
    "match_id": 2518745619,
    "duration (seconds)": 1822,
    "match_patch": "(2518745619,6.88)",
    "Radiant Team": "Beyond_Infinity",
    "radiant_score": 15,
    "Dire Team": "",
    "dire_score": 25,
    "Winner": "Dire"
  },
  {
    "date": "2016-07-21T00:00:00.000Z",
    "match_id": 2518831064,
    "duration (seconds)": 1618,
    "match_patch": "(2518831064,6.88)",
    "Radiant Team": "Invisible Wings",
    "radiant_score": 28,
    "Dire Team": "Team MuGiWaRA",
    "dire_score": 10,
    "Winner": "Radiant"
  },
  {
    "date": "2016-07-21T00:00:00.000Z",
    "match_id": 2518855634,
    "duration (seconds)": 2234,
    "match_patch": "(2518855634,6.88)",
    "Radiant Team": "FataL [F]ormation",
    "radiant_score": 30,
    "Dire Team": "",
    "dire_score": 51,
    "Winner": "Dire"
  },
  {
    "date": "2016-07-21T00:00:00.000Z",
    "match_id": 2518864618,
    "duration (seconds)": 2141,
    "match_patch": "(2518864618,6.88)",
    "Radiant Team": "Danish Bears",
    "radiant_score": 43,
    "Dire Team": "Fantastic Five",
    "dire_score": 23,
    "Winner": "Radiant"
  },
  {
    "date": "2016-07-21T00:00:00.000Z",
    "match_id": 2518906276,
    "duration (seconds)": 1949,
    "match_patch": "(2518906276,6.88)",
    "Radiant Team": "Zero Co-ordination-",
    "radiant_score": 10,
    "Dire Team": "MeeT YouR Mak3rS",
    "dire_score": 35,
    "Winner": "Dire"
  },
  {
    "date": "2016-07-21T00:00:00.000Z",
    "match_id": 2519003016,
    "duration (seconds)": 3965,
    "match_patch": "(2519003016,6.88)",
    "Radiant Team": "Fantastic Five",
    "radiant_score": 27,
    "Dire Team": "Danish Bears",
    "dire_score": 34,
    "Winner": "Dire"
  },
  {
    "date": "2016-07-21T00:00:00.000Z",
    "match_id": 2519026101,
    "duration (seconds)": 1541,
    "match_patch": "(2519026101,6.88)",
    "Radiant Team": "Aero Esports",
    "radiant_score": 33,
    "Dire Team": "Team MisCommuNicaTioN",
    "dire_score": 17,
    "Winner": "Radiant"
  },
  {
    "date": "2016-07-21T00:00:00.000Z",
    "match_id": 2519104109,
    "duration (seconds)": 2569,
    "match_patch": "(2519104109,6.88)",
    "Radiant Team": "Noobs. inc",
    "radiant_score": 23,
    "Dire Team": "Team Retribution",
    "dire_score": 33,
    "Winner": "Dire"
  },
  {
    "date": "2016-07-21T00:00:00.000Z",
    "match_id": 2519118696,
    "duration (seconds)": 2741,
    "match_patch": "(2519118696,6.88)",
    "Radiant Team": "King Arthur & 4 Knights",
    "radiant_score": 43,
    "Dire Team": "Nyx.Nyx.Nyx",
    "dire_score": 22,
    "Winner": "Radiant"
  },
  {
    "date": "2016-07-21T00:00:00.000Z",
    "match_id": 2519205206,
    "duration (seconds)": 2500,
    "match_patch": "(2519205206,6.88)",
    "Radiant Team": "Fnatic",
    "radiant_score": 26,
    "Dire Team": "Natus Vincere",
    "dire_score": 13,
    "Winner": "Radiant"
  },
  {
    "date": "2016-07-21T00:00:00.000Z",
    "match_id": 2519304127,
    "duration (seconds)": 1955,
    "match_patch": "(2519304127,6.88)",
    "Radiant Team": "Natus Vincere",
    "radiant_score": 31,
    "Dire Team": "Fnatic",
    "dire_score": 17,
    "Winner": "Radiant"
  },
  {
    "date": "2016-07-21T00:00:00.000Z",
    "match_id": 2519381339,
    "duration (seconds)": 821,
    "match_patch": "(2519381339,6.88)",
    "Radiant Team": "Natus Vincere",
    "radiant_score": 24,
    "Dire Team": "Fnatic",
    "dire_score": 5,
    "Winner": "Radiant"
  },
  {
    "date": "2016-07-21T00:00:00.000Z",
    "match_id": 2519500261,
    "duration (seconds)": 2226,
    "match_patch": "(2519500261,6.88)",
    "Radiant Team": "friends",
    "radiant_score": 15,
    "Dire Team": "123",
    "dire_score": 31,
    "Winner": "Dire"
  },
  {
    "date": "2016-07-21T00:00:00.000Z",
    "match_id": 2519578655,
    "duration (seconds)": 1927,
    "match_patch": "(2519578655,6.88)",
    "Radiant Team": "friends",
    "radiant_score": 15,
    "Dire Team": "123",
    "dire_score": 28,
    "Winner": "Dire"
  },
  {
    "date": "2016-07-21T00:00:00.000Z",
    "match_id": 2519656393,
    "duration (seconds)": 3472,
    "match_patch": "(2519656393,6.88)",
    "Radiant Team": "Infamous、",
    "radiant_score": 24,
    "Dire Team": "paiN Gaming",
    "dire_score": 35,
    "Winner": "Dire"
  },
  {
    "date": "2016-07-21T00:00:00.000Z",
    "match_id": 2519681958,
    "duration (seconds)": 2007,
    "match_patch": "(2519681958,6.88)",
    "Radiant Team": "cdec.y",
    "radiant_score": 9,
    "Dire Team": "Evil Geniuses",
    "dire_score": 16,
    "Winner": "Dire"
  }
]
