[
  {
    "date": "2017-11-15T00:00:00.000Z",
    "match_id": 3562576369,
    "duration (seconds)": 1389,
    "match_patch": "(3562576369,7.07)",
    "Radiant Team": "VGJ Storm",
    "radiant_score": 20,
    "Dire Team": "BLUE PIKACHU",
    "dire_score": 14,
    "Winner": "Radiant"
  },
  {
    "date": "2017-11-15T00:00:00.000Z",
    "match_id": 3562611021,
    "duration (seconds)": 1902,
    "match_patch": "(3562611021,7.07)",
    "Radiant Team": "BLUE PIKACHU",
    "radiant_score": 20,
    "Dire Team": "VGJ Storm",
    "dire_score": 39,
    "Winner": "Dire"
  },
  {
    "date": "2017-11-15T00:00:00.000Z",
    "match_id": 3562748886,
    "duration (seconds)": 1784,
    "match_patch": "(3562748886,7.07)",
    "Radiant Team": "Team Waooo",
    "radiant_score": 22,
    "Dire Team": "ForTheDream",
    "dire_score": 13,
    "Winner": "Radiant"
  },
  {
    "date": "2017-11-15T00:00:00.000Z",
    "match_id": 3562810513,
    "duration (seconds)": 2834,
    "match_patch": "(3562810513,7.07)",
    "Radiant Team": "ForTheDream",
    "radiant_score": 38,
    "Dire Team": "Team Waooo",
    "dire_score": 38,
    "Winner": "Dire"
  },
  {
    "date": "2017-11-15T00:00:00.000Z",
    "match_id": 3562908209,
    "duration (seconds)": 1682,
    "match_patch": "(3562908209,7.07)",
    "Radiant Team": "Sun Gaming",
    "radiant_score": 10,
    "Dire Team": "Newbee.Young",
    "dire_score": 21,
    "Winner": "Dire"
  },
  {
    "date": "2017-11-15T00:00:00.000Z",
    "match_id": 3562933432,
    "duration (seconds)": 1689,
    "match_patch": "(3562933432,7.07)",
    "Radiant Team": "Fox Gaming Youth",
    "radiant_score": 29,
    "Dire Team": "Yellow Solo Mid Reborn",
    "dire_score": 19,
    "Winner": "Radiant"
  },
  {
    "date": "2017-11-15T00:00:00.000Z",
    "match_id": 3562940116,
    "duration (seconds)": 2144,
    "match_patch": "(3562940116,7.07)",
    "Radiant Team": "Nah Bro",
    "radiant_score": 19,
    "Dire Team": "Team Question",
    "dire_score": 42,
    "Winner": "Dire"
  },
  {
    "date": "2017-11-15T00:00:00.000Z",
    "match_id": 3562942078,
    "duration (seconds)": 2642,
    "match_patch": "(3562942078,7.07)",
    "Radiant Team": "Unlucky",
    "radiant_score": 39,
    "Dire Team": "Robot House",
    "dire_score": 36,
    "Winner": "Radiant"
  },
  {
    "date": "2017-11-15T00:00:00.000Z",
    "match_id": 3562971666,
    "duration (seconds)": 2718,
    "match_patch": "(3562971666,7.07)",
    "Radiant Team": "Newbee.Young",
    "radiant_score": 21,
    "Dire Team": "Sun Gaming",
    "dire_score": 34,
    "Winner": "Dire"
  },
  {
    "date": "2017-11-15T00:00:00.000Z",
    "match_id": 3562994282,
    "duration (seconds)": 2525,
    "match_patch": "(3562994282,7.07)",
    "Radiant Team": "Yellow Solo Mid Reborn",
    "radiant_score": 32,
    "Dire Team": "Fox Gaming Youth",
    "dire_score": 51,
    "Winner": "Dire"
  },
  {
    "date": "2017-11-15T00:00:00.000Z",
    "match_id": 3563027686,
    "duration (seconds)": 2351,
    "match_patch": "(3563027686,7.07)",
    "Radiant Team": "Unlucky",
    "radiant_score": 48,
    "Dire Team": "Robot House",
    "dire_score": 24,
    "Winner": "Radiant"
  },
  {
    "date": "2017-11-15T00:00:00.000Z",
    "match_id": 3563042575,
    "duration (seconds)": 1252,
    "match_patch": "(3563042575,7.07)",
    "Radiant Team": "Team Question",
    "radiant_score": 7,
    "Dire Team": "Nah Bro",
    "dire_score": 29,
    "Winner": "Dire"
  },
  {
    "date": "2017-11-15T00:00:00.000Z",
    "match_id": 3563098098,
    "duration (seconds)": 1929,
    "match_patch": "(3563098098,7.07)",
    "Radiant Team": "Nah Bro",
    "radiant_score": 25,
    "Dire Team": "Team Question",
    "dire_score": 32,
    "Winner": "Dire"
  },
  {
    "date": "2017-11-15T00:00:00.000Z",
    "match_id": 3563102080,
    "duration (seconds)": 1633,
    "match_patch": "(3563102080,7.07)",
    "Radiant Team": "TNC Predator",
    "radiant_score": 10,
    "Dire Team": "Mineski.亿鼎博",
    "dire_score": 25,
    "Winner": "Dire"
  },
  {
    "date": "2017-11-15T00:00:00.000Z",
    "match_id": 3563110560,
    "duration (seconds)": 2926,
    "match_patch": "(3563110560,7.07)",
    "Radiant Team": "Rock Gaming",
    "radiant_score": 28,
    "Dire Team": "ForTheDream",
    "dire_score": 29,
    "Winner": "Dire"
  },
  {
    "date": "2017-11-15T00:00:00.000Z",
    "match_id": 3563181598,
    "duration (seconds)": 1850,
    "match_patch": "(3563181598,7.07)",
    "Radiant Team": "TNC Predator",
    "radiant_score": 24,
    "Dire Team": "Mineski.亿鼎博",
    "dire_score": 20,
    "Winner": "Radiant"
  },
  {
    "date": "2017-11-15T00:00:00.000Z",
    "match_id": 3563233343,
    "duration (seconds)": 1877,
    "match_patch": "(3563233343,7.07)",
    "Radiant Team": "ForTheDream",
    "radiant_score": 23,
    "Dire Team": "Rock Gaming",
    "dire_score": 20,
    "Winner": "Radiant"
  },
  {
    "date": "2017-11-15T00:00:00.000Z",
    "match_id": 3563273489,
    "duration (seconds)": 3668,
    "match_patch": "(3563273489,7.07)",
    "Radiant Team": "TNC Predator",
    "radiant_score": 38,
    "Dire Team": "Mineski.亿鼎博",
    "dire_score": 35,
    "Winner": "Radiant"
  },
  {
    "date": "2017-11-15T00:00:00.000Z",
    "match_id": 3563513021,
    "duration (seconds)": 3376,
    "match_patch": "(3563513021,7.07)",
    "Radiant Team": "Cullies",
    "radiant_score": 47,
    "Dire Team": "The Council",
    "dire_score": 54,
    "Winner": "Dire"
  },
  {
    "date": "2017-11-15T00:00:00.000Z",
    "match_id": 3563631724,
    "duration (seconds)": 1565,
    "match_patch": "(3563631724,7.07)",
    "Radiant Team": "Double Dimension",
    "radiant_score": 30,
    "Dire Team": "M19",
    "dire_score": 12,
    "Winner": "Radiant"
  },
  {
    "date": "2017-11-15T00:00:00.000Z",
    "match_id": 3563705876,
    "duration (seconds)": 2434,
    "match_patch": "(3563705876,7.07)",
    "Radiant Team": "M19",
    "radiant_score": 23,
    "Dire Team": "Double Dimension",
    "dire_score": 46,
    "Winner": "Dire"
  },
  {
    "date": "2017-11-15T00:00:00.000Z",
    "match_id": 3563798494,
    "duration (seconds)": 1316,
    "match_patch": "(3563798494,7.07)",
    "Radiant Team": "OpTic Gaming",
    "radiant_score": 21,
    "Dire Team": "idc mmr",
    "dire_score": 11,
    "Winner": "Radiant"
  },
  {
    "date": "2017-11-15T00:00:00.000Z",
    "match_id": 3563801635,
    "duration (seconds)": 1279,
    "match_patch": "(3563801635,7.07)",
    "Radiant Team": "Immortals",
    "radiant_score": 21,
    "Dire Team": "CES",
    "dire_score": 6,
    "Winner": "Radiant"
  },
  {
    "date": "2017-11-15T00:00:00.000Z",
    "match_id": 3563853766,
    "duration (seconds)": 1107,
    "match_patch": "(3563853766,7.07)",
    "Radiant Team": "OpTic Gaming",
    "radiant_score": 23,
    "Dire Team": "idc mmr",
    "dire_score": 3,
    "Winner": "Radiant"
  },
  {
    "date": "2017-11-15T00:00:00.000Z",
    "match_id": 3563857761,
    "duration (seconds)": 1921,
    "match_patch": "(3563857761,7.07)",
    "Radiant Team": "Immortals",
    "radiant_score": 40,
    "Dire Team": "CES",
    "dire_score": 19,
    "Winner": "Radiant"
  },
  {
    "date": "2017-11-15T00:00:00.000Z",
    "match_id": 3563921943,
    "duration (seconds)": 3096,
    "match_patch": "(3563921943,7.07)",
    "Radiant Team": "No Creativity",
    "radiant_score": 35,
    "Dire Team": "Team Singularity",
    "dire_score": 39,
    "Winner": "Dire"
  },
  {
    "date": "2017-11-15T00:00:00.000Z",
    "match_id": 3564012840,
    "duration (seconds)": 1588,
    "match_patch": "(3564012840,7.07)",
    "Radiant Team": "Team Singularity",
    "radiant_score": 32,
    "Dire Team": "No Creativity",
    "dire_score": 13,
    "Winner": "Radiant"
  },
  {
    "date": "2017-11-15T00:00:00.000Z",
    "match_id": 3564047563,
    "duration (seconds)": 1931,
    "match_patch": "(3564047563,7.07)",
    "Radiant Team": "OpTic Gaming",
    "radiant_score": 31,
    "Dire Team": "VGJ Storm",
    "dire_score": 7,
    "Winner": "Radiant"
  },
  {
    "date": "2017-11-15T00:00:00.000Z",
    "match_id": 3564091037,
    "duration (seconds)": 1226,
    "match_patch": "(3564091037,7.07)",
    "Radiant Team": "OpTic Gaming",
    "radiant_score": 5,
    "Dire Team": "VGJ Storm",
    "dire_score": 27,
    "Winner": "Dire"
  }
]
