[
  {
    "match_id": 3584868656,
    "avg": "3517.0000000000000000",
    "count": 1,
    "winrate": 0.5,
    "winrate_wilson": 0.236589593615487,
    "sum": 35170,
    "min": 3517,
    "max": 3517,
    "match_patch": "(3584868656,7.07)",
    "radiant_team_id": 1905619,
    "dire_team_id": 5066008,
    "radiant_win": true,
    "radiant_score": 33,
    "dire_score": 31,
    "start_time": 1511747773,
    "League": "Uprise Champions Cup: Special"
  },
  {
    "match_id": 3586335331,
    "avg": "3467.0000000000000000",
    "count": 1,
    "winrate": 0.5,
    "winrate_wilson": 0.236589593615487,
    "sum": 34670,
    "min": 3467,
    "max": 3467,
    "match_patch": "(3586335331,7.07)",
    "radiant_team_id": 1846548,
    "dire_team_id": 5054122,
    "radiant_win": false,
    "radiant_score": 34,
    "dire_score": 46,
    "start_time": 1511815094,
    "League": "Uprise Champions Cup: Special"
  },
  {
    "match_id": 3586166561,
    "avg": "2916.0000000000000000",
    "count": 1,
    "winrate": 0.5,
    "winrate_wilson": 0.236589593615487,
    "sum": 29160,
    "min": 2916,
    "max": 2916,
    "match_patch": "(3586166561,7.07)",
    "radiant_team_id": 3704482,
    "dire_team_id": 26,
    "radiant_win": true,
    "radiant_score": 30,
    "dire_score": 31,
    "start_time": 1511806266,
    "League": "Uprise Champions Cup: Special"
  },
  {
    "match_id": 3586254327,
    "avg": "2903.0000000000000000",
    "count": 1,
    "winrate": 0.5,
    "winrate_wilson": 0.236589593615487,
    "sum": 29030,
    "min": 2903,
    "max": 2903,
    "match_patch": "(3586254327,7.07)",
    "radiant_team_id": 1846548,
    "dire_team_id": 5054122,
    "radiant_win": false,
    "radiant_score": 30,
    "dire_score": 44,
    "start_time": 1511810565,
    "League": "Uprise Champions Cup: Special"
  },
  {
    "match_id": 3585198789,
    "avg": "2695.0000000000000000",
    "count": 1,
    "winrate": 0.5,
    "winrate_wilson": 0.236589593615487,
    "sum": 26950,
    "min": 2695,
    "max": 2695,
    "match_patch": "(3585198789,7.07)",
    "radiant_team_id": 2626685,
    "dire_team_id": 5000254,
    "radiant_win": true,
    "radiant_score": 28,
    "dire_score": 17,
    "start_time": 1511768191,
    "League": "ProDotA Cup Series"
  },
  {
    "match_id": 3584939560,
    "avg": "2371.0000000000000000",
    "count": 1,
    "winrate": 0.5,
    "winrate_wilson": 0.236589593615487,
    "sum": 23710,
    "min": 2371,
    "max": 2371,
    "match_patch": "(3584939560,7.07)",
    "radiant_team_id": 1905619,
    "dire_team_id": 5066008,
    "radiant_win": true,
    "radiant_score": 34,
    "dire_score": 23,
    "start_time": 1511752775,
    "League": "Uprise Champions Cup: Special"
  },
  {
    "match_id": 3585137621,
    "avg": "2103.0000000000000000",
    "count": 1,
    "winrate": 0.5,
    "winrate_wilson": 0.236589593615487,
    "sum": 21030,
    "min": 2103,
    "max": 2103,
    "match_patch": "(3585137621,7.07)",
    "radiant_team_id": 5000254,
    "dire_team_id": 2626685,
    "radiant_win": true,
    "radiant_score": 37,
    "dire_score": 25,
    "start_time": 1511764904,
    "League": "ProDotA Cup Series"
  },
  {
    "match_id": 3585829671,
    "avg": "2043.0000000000000000",
    "count": 1,
    "winrate": 0.5,
    "winrate_wilson": 0.236589593615487,
    "sum": 20430,
    "min": 2043,
    "max": 2043,
    "match_patch": "(3585829671,7.07)",
    "radiant_team_id": 3846296,
    "dire_team_id": 2761738,
    "radiant_win": true,
    "radiant_score": 27,
    "dire_score": 16,
    "start_time": 1511793065,
    "League": "ESL India Premiership - 2017 Edition"
  },
  {
    "match_id": 3584825195,
    "avg": "1740.0000000000000000",
    "count": 1,
    "winrate": 0.5,
    "winrate_wilson": 0.236589593615487,
    "sum": 17400,
    "min": 1740,
    "max": 1740,
    "match_patch": "(3584825195,7.07)",
    "radiant_team_id": 1905619,
    "dire_team_id": 5066008,
    "radiant_win": false,
    "radiant_score": 8,
    "dire_score": 25,
    "start_time": 1511744496,
    "League": "Uprise Champions Cup: Special"
  },
  {
    "match_id": 3586080060,
    "avg": "1739.0000000000000000",
    "count": 1,
    "winrate": 0.5,
    "winrate_wilson": 0.236589593615487,
    "sum": 17390,
    "min": 1739,
    "max": 1739,
    "match_patch": "(3586080060,7.07)",
    "radiant_team_id": 3704482,
    "dire_team_id": 26,
    "radiant_win": true,
    "radiant_score": 33,
    "dire_score": 17,
    "start_time": 1511802427,
    "League": "Uprise Champions Cup: Special"
  },
  {
    "match_id": 3585973251,
    "avg": "1708.0000000000000000",
    "count": 1,
    "winrate": 0.5,
    "winrate_wilson": 0.236589593615487,
    "sum": 17080,
    "min": 1708,
    "max": 1708,
    "match_patch": "(3585973251,7.07)",
    "radiant_team_id": 5070841,
    "dire_team_id": 5054122,
    "radiant_win": false,
    "radiant_score": 25,
    "dire_score": 47,
    "start_time": 1511798109,
    "League": "ProDotA Cup Series"
  },
  {
    "match_id": 3586457488,
    "avg": "1585.0000000000000000",
    "count": 1,
    "winrate": 0.5,
    "winrate_wilson": 0.236589593615487,
    "sum": 15850,
    "min": 1585,
    "max": 1585,
    "match_patch": "(3586457488,7.07)",
    "radiant_team_id": 5028104,
    "dire_team_id": 1905619,
    "radiant_win": true,
    "radiant_score": 28,
    "dire_score": 12,
    "start_time": 1511823683,
    "League": "Uprise Champions Cup: Special"
  },
  {
    "match_id": 3585822619,
    "avg": "1403.0000000000000000",
    "count": 1,
    "winrate": 0.5,
    "winrate_wilson": 0.236589593615487,
    "sum": 14030,
    "min": 1403,
    "max": 1403,
    "match_patch": "(3585822619,7.07)",
    "radiant_team_id": 4962421,
    "dire_team_id": 3928293,
    "radiant_win": true,
    "radiant_score": 26,
    "dire_score": 12,
    "start_time": 1511793067,
    "League": "ESL India Premiership - 2017 Edition"
  },
  {
    "match_id": 3586488553,
    "avg": "1067.0000000000000000",
    "count": 1,
    "winrate": 0.5,
    "winrate_wilson": 0.236589593615487,
    "sum": 10670,
    "min": 1067,
    "max": 1067,
    "match_patch": "(3586488553,7.07)",
    "radiant_team_id": 1905619,
    "dire_team_id": 5028104,
    "radiant_win": false,
    "radiant_score": 5,
    "dire_score": 15,
    "start_time": 1511826384,
    "League": "Uprise Champions Cup: Special"
  },
  {
    "match_id": 3585099492,
    "avg": "942.0000000000000000",
    "count": 1,
    "winrate": 0.5,
    "winrate_wilson": 0.236589593615487,
    "sum": 9420,
    "min": 942,
    "max": 942,
    "match_patch": "(3585099492,7.07)",
    "radiant_team_id": 2626685,
    "dire_team_id": 5000254,
    "radiant_win": true,
    "radiant_score": 17,
    "dire_score": 4,
    "start_time": 1511762729,
    "League": "ProDotA Cup Series"
  }
]
